catslab/__init__.py
catslab/finance/__init__.py
catslab/finance/black_scholes_equation.py
catslab/word/__init__.py
catslab/word/mecab.py
catslab-0.0.1.dist-info/METADATA
catslab-0.0.1.dist-info/WHEEL
catslab-0.0.1.dist-info/top_level.txt
catslab-0.0.1.dist-info/RECORD
